clygon/__init__.py
clygon/clygon.py
clygon/shapes.py
clygon-0.0.5.dist-info/METADATA
clygon-0.0.5.dist-info/WHEEL
clygon-0.0.5.dist-info/top_level.txt
clygon-0.0.5.dist-info/RECORD
