Metadata-Version: 2.1
Name: clygon
Version: 0.0.5
Summary: A simple library to calculate anything and everything about circles and polygons.
Home-page: UNKNOWN
Author: Krishay Rastogi
Author-email: <krishayras@gmail.com>
License: UNKNOWN
Keywords: python,math,geometry,polygons,circles,angles,sides
Platform: UNKNOWN
Classifier: Development Status :: 1 - Planning
Classifier: Intended Audience :: Developers
Classifier: Programming Language :: Python :: 3
Classifier: Operating System :: Unix
Classifier: Operating System :: MacOS :: MacOS X
Classifier: Operating System :: Microsoft :: Windows
